tenks/__init__.py
tenks/version.py
tenks-2.0.0.dist-info/AUTHORS
tenks-2.0.0.dist-info/LICENSE
tenks-2.0.0.dist-info/METADATA
tenks-2.0.0.dist-info/WHEEL
tenks-2.0.0.dist-info/pbr.json
tenks-2.0.0.dist-info/top_level.txt
tenks-2.0.0.dist-info/RECORD
